elementarise/__init__.py
elementarise/__main__.py
elementarise/definitions.py
elementarise/drawing.py
elementarise/helpers.py
elementarise/metrics.py
elementarise/param_generation.py
elementarise/runtime.py
elementarise/utils.py
elementarise-0.1.4.dist-info/LICENSE
elementarise-0.1.4.dist-info/METADATA
elementarise-0.1.4.dist-info/WHEEL
elementarise-0.1.4.dist-info/top_level.txt
elementarise-0.1.4.dist-info/RECORD
