Metadata-Version: 2.1
Name: elementarise
Version: 0.1.4
Summary: Generate elementarised image
Home-page: https://github.com/Matesxs/elementarise
Author: Martin Douša
Author-email: martindousa186@gmail.com
License: MIT
Classifier: Development Status :: 5 - Production/Stable
Classifier: Intended Audience :: Developers
Classifier: Intended Audience :: End Users/Desktop
Classifier: Intended Audience :: Science/Research
Classifier: License :: OSI Approved :: MIT License
Classifier: Operating System :: OS Independent
Classifier: Programming Language :: Python :: 3.7
Classifier: Topic :: Multimedia
Classifier: Topic :: Utilities
License-File: LICENSE
Requires-Dist: numpy (~=1.22.4)
Requires-Dist: opencv-python (~=4.6.0.66)
Requires-Dist: Pillow (~=9.2.0)
Requires-Dist: numba (==0.56.2)
Requires-Dist: tqdm (==4.64.1)
